docs/assets/viva_logo.png
viva/__init__.py
viva/env.py
viva/gui.py
viva/launcher.py
viva/main.py
viva/GUI/forest-dark.tcl
viva/GUI/forest-light.tcl
viva/GUI/forest-dark/border-accent-hover.png
viva/GUI/forest-dark/border-accent.png
viva/GUI/forest-dark/border-basic.png
viva/GUI/forest-dark/border-hover.png
viva/GUI/forest-dark/border-invalid.png
viva/GUI/forest-dark/card.png
viva/GUI/forest-dark/check-accent.png
viva/GUI/forest-dark/check-basic.png
viva/GUI/forest-dark/check-hover.png
viva/GUI/forest-dark/check-tri-accent.png
viva/GUI/forest-dark/check-tri-basic.png
viva/GUI/forest-dark/check-tri-hover.png
viva/GUI/forest-dark/check-unsel-accent.png
viva/GUI/forest-dark/check-unsel-basic.png
viva/GUI/forest-dark/check-unsel-hover.png
viva/GUI/forest-dark/check-unsel-pressed.png
viva/GUI/forest-dark/combo-button-basic.png
viva/GUI/forest-dark/combo-button-focus.png
viva/GUI/forest-dark/combo-button-hover.png
viva/GUI/forest-dark/down.png
viva/GUI/forest-dark/empty.png
viva/GUI/forest-dark/hor-accent.png
viva/GUI/forest-dark/hor-basic.png
viva/GUI/forest-dark/hor-hover.png
viva/GUI/forest-dark/notebook.png
viva/GUI/forest-dark/off-accent.png
viva/GUI/forest-dark/off-basic.png
viva/GUI/forest-dark/off-hover.png
viva/GUI/forest-dark/on-accent.png
viva/GUI/forest-dark/on-basic.png
viva/GUI/forest-dark/on-hover.png
viva/GUI/forest-dark/radio-accent.png
viva/GUI/forest-dark/radio-basic.png
viva/GUI/forest-dark/radio-hover.png
viva/GUI/forest-dark/radio-tri-accent.png
viva/GUI/forest-dark/radio-tri-basic.png
viva/GUI/forest-dark/radio-tri-hover.png
viva/GUI/forest-dark/radio-unsel-accent.png
viva/GUI/forest-dark/radio-unsel-basic.png
viva/GUI/forest-dark/radio-unsel-hover.png
viva/GUI/forest-dark/radio-unsel-pressed.png
viva/GUI/forest-dark/rect-accent-hover.png
viva/GUI/forest-dark/rect-accent.png
viva/GUI/forest-dark/rect-basic.png
viva/GUI/forest-dark/rect-hover.png
viva/GUI/forest-dark/right.png
viva/GUI/forest-dark/scale-hor.png
viva/GUI/forest-dark/scale-vert.png
viva_safeland-0.2.1.dist-info/licenses/LICENSE
viva_safeland-0.2.1.dist-info/METADATA
viva_safeland-0.2.1.dist-info/WHEEL
viva_safeland-0.2.1.dist-info/entry_points.txt
viva_safeland-0.2.1.dist-info/top_level.txt
viva_safeland-0.2.1.dist-info/RECORD
