Metadata-Version: 2.4
Name: viva-safeland
Version: 0.2.1
Summary: A new freeware for safe validation of vision-based navigation in aerial vehicles
License: MIT
Classifier: Development Status :: 3 - Alpha
Classifier: Intended Audience :: Developers
Classifier: Intended Audience :: Science/Research
Classifier: Programming Language :: Python :: 3
Classifier: Programming Language :: Python :: 3.12
Classifier: Operating System :: OS Independent
Classifier: Topic :: Scientific/Engineering :: Artificial Intelligence
Classifier: Topic :: Software Development :: Libraries :: Python Modules
Requires-Python: >=3.12
License-File: LICENSE
Requires-Dist: opencv-python>=4.12.0.88
Requires-Dist: pillow>=10.4.0
Requires-Dist: pygame>=2.6.1
Requires-Dist: typer>=0.17.3
Provides-Extra: docs
Requires-Dist: mkdocs>=1.6.1; extra == "docs"
Requires-Dist: mkdocs-material>=9.6.17; extra == "docs"
Requires-Dist: mkdocstrings[python]>=0.26.1; extra == "docs"
Dynamic: license-file
